nonary/__init__.py
nonary/main.py
nonary-0.2.0.dist-info/METADATA
nonary-0.2.0.dist-info/WHEEL
nonary-0.2.0.dist-info/entry_points.txt
nonary-0.2.0.dist-info/RECORD
